flexstore/__init__.py
flexstore/storage_providers/__init__.py
flexstore/storage_providers/example_provider.py.txt
flexstore-0.0.3.dist-info/WHEEL
flexstore-0.0.3.dist-info/METADATA
flexstore-0.0.3.dist-info/RECORD
