Metadata-Version: 2.1
Name: flexstore
Version: 0.0.3
Summary: 
Author: Dan Sikes
Author-email: dansikes7@gmail.com
Requires-Python: >=3.9,<4.0
Classifier: Programming Language :: Python :: 3
Classifier: Programming Language :: Python :: 3.9
Requires-Dist: boto3 (>=1.17.84,<2.0.0)
Requires-Dist: msgpack (>=1.0.2,<2.0.0)
Requires-Dist: redis (>=3.5.3,<4.0.0)
